importTime/__init__.py
importTime-1.0.3.2.dist-info/LICENSE.txt
importTime-1.0.3.2.dist-info/METADATA
importTime-1.0.3.2.dist-info/WHEEL
importTime-1.0.3.2.dist-info/top_level.txt
importTime-1.0.3.2.dist-info/RECORD
