Metadata-Version: 2.1
Name: importTime
Version: 1.0.3.2
Summary: Debug import time or use this inside of a profiler.
Home-page: https://github.com/vltmedia/importTime
Author: Justin Jaro
Author-email: info@VLTMedia.com
License: Apache License 2.0
Platform: UNKNOWN
License-File: LICENSE.txt
